csv_reader/__init__.py
csv_reader/libcsvread.py
mds_csv_reader-1.0.5.dist-info/METADATA
mds_csv_reader-1.0.5.dist-info/WHEEL
mds_csv_reader-1.0.5.dist-info/top_level.txt
mds_csv_reader-1.0.5.dist-info/RECORD
